{
  "kind": "collectionType",
  "collectionName": "orders",
  "info": {
    "singularName": "order",
    "pluralName": "orders",
    "displayName": "order",
    "description": ""
  },
  "options": {
    "draftAndPublish": true
  },
  "pluginOptions": {},
  "attributes": {
    "status": {
      "type": "enumeration",
      "enum": [
        "paid",
        "unpaid"
      ]
    },
    "product": {
      "type": "relation",
      "relation": "manyToOne",
      "target": "api::product.product",
      "inversedBy": "orders"
    },
    "user": {
      "type": "relation",
      "relation": "manyToOne",
      "target": "plugin::users-permissions.user",
      "inversedBy": "orders"
    },
    "products": {
      "type": "json"
    },
    "paymentInfo": {
      "type": "json"
    },
    "amount": {
      "type": "decimal"
    },
    "transactionid": {
      "type": "uid"
    }
  }
}
